evervault_attestation_bindings-0.4.0.dist-info/METADATA
evervault_attestation_bindings-0.4.0.dist-info/WHEEL
evervault_attestation_bindings/__init__.py
evervault_attestation_bindings/evervault_attestation_bindings.cpython-312-arm-linux-gnueabihf.so
evervault_attestation_bindings-0.4.0.dist-info/RECORD
